<Updates>
 <ApplicationName>{AnyApplication}</ApplicationName>
 <ApplicationVersion>1.0.0</ApplicationVersion>
 <Checksum>true</Checksum>
 <PackageUpdate>
  <Name>in.antonyjr.libarchive.windows.x64.msvc2019</Name>
  <DisplayName>LibArchive - MSVC 2019</DisplayName>
  <Description>LibArchive (Prebuilt for MSVC 2019)</Description>
  <Version>3.6.2</Version>
  <ReleaseDate>2023-12-10</ReleaseDate>
  <Virtual>True</Virtual>
  <Script>installscript.js</Script>
  <UpdateFile CompressedSize="9334522" OS="Any" UncompressedSize="46764116"/>
  <DownloadableArchives>msvc2019_64.7z</DownloadableArchives>
  <Licenses>
   <License file="license.txt" name="License Agreement"/>
  </Licenses>
  <SHA1>b6877b02c1b524146de4363e049c92a6559621a1</SHA1>
 </PackageUpdate>
 <PackageUpdate>
  <Name>in.antonyjr.QArchive</Name>
  <DisplayName>QArchive</DisplayName>
  <Description>Qt Wrapper for LibArchive</Description>
  <Version>2.2.8</Version>
  <ReleaseDate>2023-12-10</ReleaseDate>
  <Default>script</Default>
  <Script>installscript.js</Script>
  <UpdateFile CompressedSize="0" OS="Any" UncompressedSize="0"/>
  <Licenses>
   <License file="license.txt" name="License Agreement"/>
  </Licenses>
  <SHA1>123a24cb051e6716429f9025103977d4ad091339</SHA1>
 </PackageUpdate>
 <PackageUpdate>
  <Name>in.antonyjr.QArchive.windows.x64.msvc2019</Name>
  <DisplayName>QArchive - MSVC 2019</DisplayName>
  <Description>Qt Wrapper for LibArchive (Prebuilt for MSVC 2019)</Description>
  <Version>2.2.8</Version>
  <ReleaseDate>2023-12-10</ReleaseDate>
  <Dependencies>in.antonyjr.libarchive.windows.x64.msvc2019</Dependencies>
  <Virtual>True</Virtual>
  <Script>installscript.js</Script>
  <UpdateFile CompressedSize="893641" OS="Any" UncompressedSize="2119925"/>
  <DownloadableArchives>msvc2019_64.7z</DownloadableArchives>
  <Licenses>
   <License file="license.txt" name="License Agreement"/>
  </Licenses>
  <SHA1>328d3a1e3d8da3825e3a05f974e94ca398f1b179</SHA1>
 </PackageUpdate>
 <SHA1>3895fb6fbebd467783c610dd2f3de729be029f37</SHA1>
 <MetadataName>2023-12-10-0839_meta.7z</MetadataName>
</Updates>
